pylotte/__init__.py
pylotte/signed_pickle.py
pylotte-0.3.dist-info/METADATA
pylotte-0.3.dist-info/WHEEL
pylotte-0.3.dist-info/licenses/LICENSE.txt
pylotte-0.3.dist-info/RECORD
