Metadata-Version: 2.4
Name: pylotte
Version: 0.3
Summary: Package for signing and verifying pickle files
Project-URL: Documentation, https://github.com/alpamayo-solutions/pylotte#readme
Project-URL: Issues, https://github.com/alpamayo-solutions/pylotte/issues
Project-URL: Source, https://github.com/alpamayo-solutions/pylotte
Author-email: Alpamayo <info@alpamayo-solutions.com>
License-Expression: MIT
License-File: LICENSE.txt
Classifier: Development Status :: 4 - Beta
Classifier: Programming Language :: Python
Classifier: Programming Language :: Python :: 3.9
Classifier: Programming Language :: Python :: 3.10
Classifier: Programming Language :: Python :: 3.11
Classifier: Programming Language :: Python :: 3.12
Requires-Python: >=3.9
Requires-Dist: cryptography
Provides-Extra: dev
Requires-Dist: pytest; extra == 'dev'
Requires-Dist: ruff; extra == 'dev'
